{
    "cbsdenv": "/usr/jails",
    "cbsdcolor": false,
    "broker": "beanstalkd",
    "logfile": "/dev/stdout",
    "recomendation": "/usr/local/cbsd/modules/api.d/misc/recomendation.sh",
    "freejname": "/usr/local/cbsd/modules/api.d/misc/freejname.sh",
    "server_url": "%%SCHEMA%%://%%IP%%",
    "cloud_images_list": "/usr/local/etc/cbsd_api_cloud_images.json",
    "iso_images_list": "/usr/local/etc/cbsd_api_iso_images.json",
    "beanstalkd": {
      "uri": "127.0.0.1:11300",
      "tube": "cbsd_zpool1",
      "reply_tube_prefix": "cbsd_zpool1_result_id",
      "reconnect_timeout": 5,
      "reserve_timeout": 5,
      "publish_timeout": 5,
      "logdir": "/var/log/cbsdmq"
    }
}
